{"address1": "No. 21, Wufu 3rd Road", "address2": "4th Floor Qianjin District", "city": "Kaohsiung", "country": "Taiwan", "phone": "886 7 271 1121", "website": "https://www.southeastcement.com.tw", "industry": "Building Materials", "industryDisp": "Building Materials", "sector": "Basic Materials", "longBusinessSummary": "Southeast Cement Corporation engages in the production and sale of cement in Taiwan. The company offers Portland I and Portland II cement, hearthstone, kiln stone powder, cement processed products, and premixed concrete. It also engages in reinvestment business and waste removal treatment activities, as well as the development, rental, and sale of residential and office buildings. The company was founded in 1956 and is based in Kaohsiung, Taiwan.", "companyOfficers": [{"maxAge": 1, "name": "Mr. Kuan-Hua  Chen", "title": "Pres & Vice Chairman", "exercisedValue": 0, "unexercisedValue": 0}, {"maxAge": 1, "name": "Mr. Hsin-Han  Huang", "title": "Mang. of Fin. Department", "exercisedValue": 0, "unexercisedValue": 0}], "maxAge": 86400, "priceHint": 2, "previousClose": 18.75, "open": 18.7, "dayLow": 18.65, "dayHigh": 18.8, "regularMarketPreviousClose": 18.75, "regularMarketOpen": 18.7, "regularMarketDayLow": 18.65, "regularMarketDayHigh": 18.8, "dividendRate": 0.2, "dividendYield": 0.0107, "exDividendDate": 1658361600, "payoutRatio": 0.76919997, "fiveYearAvgDividendYield": 0.68, "beta": -0.048705, "trailingPE": 72.30769, "volume": 206000, "regularMarketVolume": 206000, "averageVolume": 204591, "averageVolume10days": 361381, "averageDailyVolume10Day": 361381, "bid": 18.7, "ask": 18.75, "bidSize": 0, "askSize": 0, "marketCap": 10742526976, "fiftyTwoWeekLow": 16.7, "fiftyTwoWeekHigh": 21.15, "priceToSalesTrailing12Months": 5.987981, "fiftyDayAverage": 18.004, "twoHundredDayAverage": 17.967, "trailingAnnualDividendRate": 0.1, "trailingAnnualDividendYield": 0.0053333333, "currency": "TWD", "enterpriseValue": 12320075776, "profitMargins": 0.08307999, "floatShares": 281393104, "sharesOutstanding": 569886976, "heldPercentInsiders": 0.68651, "heldPercentInstitutions": 0.00588, "impliedSharesOutstanding": 0, "bookValue": 15.146, "priceToBook": 1.2412518, "lastFiscalYearEnd": 1672444800, "nextFiscalYearEnd": 1703980800, "mostRecentQuarter": 1672444800, "earningsQuarterlyGrowth": 4.675, "netIncomeToCommon": 149043008, "trailingEps": 0.26, "lastSplitFactor": "105:100", "lastSplitDate": 1092268800, "enterpriseToRevenue": 6.867, "enterpriseToEbitda": -1593.594, "52WeekChange": -0.06716418, "SandP52WeekChange": 0.026524067, "lastDividendValue": 0.2, "lastDividendDate": 1658361600, "exchange": "TAI", "quoteType": "EQUITY", "symbol": "1110.TW", "underlyingSymbol": "1110.TW", "shortName": "SOUTH EAST CEMENT CO LTD.", "longName": "Southeast Cement Corporation", "firstTradeDateEpochUtc": 946947600, "timeZoneFullName": "Asia/Taipei", "timeZoneShortName": "CST", "uuid": "fcfccb25-e8e3-3da4-8e00-8b3e30f452ae", "messageBoardId": "finmb_20360113", "gmtOffSetMilliseconds": 28800000, "currentPrice": 18.8, "recommendationKey": "none", "totalCash": 1018428992, "totalCashPerShare": 1.787, "ebitda": -7731000, "totalDebt": 2586656000, "quickRatio": 0.597, "currentRatio": 1.044, "totalRevenue": 1794014976, "debtToEquity": 29.641, "revenuePerShare": 3.148, "returnOnAssets": -0.0017200001, "returnOnEquity": 0.0124, "grossProfits": 121279000, "freeCashflow": -310880128, "operatingCashflow": -276638016, "earningsGrowth": 4.675, "revenueGrowth": 0.119, "grossMargins": 0.067600004, "ebitdaMargins": -0.0043099998, "operatingMargins": -0.01756, "financialCurrency": "TWD", "trailingPegRatio": null}