{"address1": "No. 296, Xinyi Road", "address2": "3rd Floor Section 4 Da\u2019an District", "city": "Taipei", "zip": "106", "country": "Taiwan", "phone": "886 2 2706 2191", "website": "https://www.heysong.com.tw", "industry": "Beverages\u2014Non-Alcoholic", "sector": "Consumer Defensive", "longBusinessSummary": "Hey Song Corporation produces, distributes, and sells beverages primarily in Taiwan. It offers carbonated drinks under the HeySong Sarsaparilla, C&C, and HeySong Soda brands; coffee under the Wincafe brand; tea under the HeySong ExploringTea, HeySong Camellia Green Tea, and HeySong Tea brands; and sports drinks under the HeySong FIN brand. The company also provides liqueur drinks under the CHOYA brand; sake under the Kuromatsu Hakushika Sake, Takashimizu, and KENBISHI brands; Chinese spirits under the 58 KinKao brand; and wine under the Hardys, EVO, Kumala, Banrock Station, Bocopa, Sgarzi Luigi, KOALA FOREST, Vina Del Pedregal, Huat-Guiraud, Hugo Casanova, Raymond Huet, Petaluma, Grant Burge, Arras, ST.Hallett, and PPB brands. In addition, it offers juices under the HeySong Juice and Oasis Juice brands; and water and Remy Cointreau products. Hey Song Corporation was founded in 1925 and is headquartered in Taipei, Taiwan.", "companyOfficers": [{"maxAge": 1, "name": "Mr. Pin-Tang  Chang", "title": "Chairman & Pres", "exercisedValue": 0, "unexercisedValue": 0}, {"maxAge": 1, "name": "Mr. Chu-Tsan  Du", "title": "Director of Fin. Division", "exercisedValue": 0, "unexercisedValue": 0}, {"maxAge": 1, "name": "Mr. Chien-Lun  LI", "title": "Director of Sales Division 1&2", "exercisedValue": 0, "unexercisedValue": 0}, {"maxAge": 1, "name": "Mr. Chien-Chang  Chang", "title": "Special Assistant & Director", "exercisedValue": 0, "unexercisedValue": 0}, {"maxAge": 1, "name": "Mr. Yi-Hsiu  Chien", "title": "Mang. of Gen. Affairs Department & Head of Corp. Governance", "exercisedValue": 0, "unexercisedValue": 0}], "maxAge": 86400, "priceHint": 2, "previousClose": 36.05, "open": 36.05, "dayLow": 35.85, "dayHigh": 36.2, "regularMarketPreviousClose": 36.05, "regularMarketOpen": 36.05, "regularMarketDayLow": 35.85, "regularMarketDayHigh": 36.2, "dividendRate": 1.8, "dividendYield": 0.0498, "exDividendDate": 1688947200, "payoutRatio": 0.77269995, "fiveYearAvgDividendYield": 5.09, "beta": 0.189071, "trailingPE": 16.318182, "volume": 294433, "regularMarketVolume": 294433, "averageVolume": 331009, "averageVolume10days": 252923, "averageDailyVolume10Day": 252923, "bid": 35.9, "ask": 35.95, "marketCap": 14427169792, "fiftyTwoWeekLow": 32.1, "fiftyTwoWeekHigh": 36.5, "priceToSalesTrailing12Months": 1.5093554, "fiftyDayAverage": 35.175, "twoHundredDayAverage": 33.787, "trailingAnnualDividendRate": 1.8, "trailingAnnualDividendYield": 0.04993065, "currency": "TWD", "enterpriseValue": 14024380416, "profitMargins": 0.092709996, "floatShares": 259789508, "sharesOutstanding": 401871008, "heldPercentInsiders": 0.24744, "heldPercentInstitutions": 0.02338, "impliedSharesOutstanding": 0, "bookValue": 45.65, "priceToBook": 0.7864184, "lastFiscalYearEnd": 1672444800, "nextFiscalYearEnd": 1703980800, "mostRecentQuarter": 1672444800, "earningsQuarterlyGrowth": -0.261, "netIncomeToCommon": 886134976, "trailingEps": 2.2, "lastSplitFactor": "0:1", "lastSplitDate": 1383177600, "enterpriseToRevenue": 1.467, "enterpriseToEbitda": 15.22, "52WeekChange": 0.009776592, "SandP52WeekChange": -0.033239067, "lastDividendValue": 1.8, "lastDividendDate": 1688947200, "exchange": "TAI", "quoteType": "EQUITY", "symbol": "1234.TW", "underlyingSymbol": "1234.TW", "shortName": "HEY SONG", "longName": "Hey Song Corporation", "firstTradeDateEpochUtc": 946947600, "timeZoneFullName": "Asia/Taipei", "timeZoneShortName": "CST", "uuid": "b44ebcb1-1e4c-3955-b017-a8657efe80ec", "messageBoardId": "finmb_9571469", "gmtOffSetMilliseconds": 28800000, "currentPrice": 35.9, "recommendationKey": "none", "totalCash": 1500280960, "totalCashPerShare": 3.733, "ebitda": 921470016, "totalDebt": 1037212032, "quickRatio": 1.214, "currentRatio": 4.023, "totalRevenue": 9558497280, "debtToEquity": 5.654, "revenuePerShare": 23.785, "returnOnAssets": 0.01632, "returnOnEquity": 0.04857, "grossProfits": 2678818000, "freeCashflow": 116253872, "operatingCashflow": 813241984, "earningsGrowth": -0.274, "revenueGrowth": 0.067, "grossMargins": 0.28026, "ebitdaMargins": 0.0964, "operatingMargins": 0.062230002, "financialCurrency": "TWD", "trailingPegRatio": null}