{"address1": "Km9, Pham Van Dong street", "address2": "Hai Thanh Ward Duong Kinh district", "city": "Hai phong", "country": "Vietnam", "phone": "84 225 3860 399", "fax": "84 225 3860 373", "website": "https://www.fulinvn.com", "industry": "Textile Manufacturing", "industryDisp": "Textile Manufacturing", "sector": "Consumer Cyclical", "longBusinessSummary": "Fulin Plastic Industry (Cayman) Holding Co., Ltd. engages in the production and sale of artificial leather and rubber fabric. The company offers latex, soft, TPU/PU, PVC solid, PVC sponge, and PVC casting leather products; tapes; PVC sheets; tarpaulins; and non-woven fabrics, as well as various embossing products. Its products are used in leather bags, shoes, furniture, vehicle, balls, raincoats, printing sheets, transparent bags, and overlays. The company was incorporated in 1997 and is headquartered in Hai Phong, Vietnam.", "companyOfficers": [{"maxAge": 1, "name": "Mr. Cheng-Hung  Huang", "title": "GM, Head of Technical R&D Department & Director", "exercisedValue": 0, "unexercisedValue": 0}, {"maxAge": 1, "name": "Mr. Wen-Hui  Chiu", "title": "Mang. of the Financial & Accounting Department, Corp. Governance Officer and Director", "exercisedValue": 0, "unexercisedValue": 0}], "maxAge": 86400, "priceHint": 2, "previousClose": 69.2, "open": 69.8, "dayLow": 69.1, "dayHigh": 70.5, "regularMarketPreviousClose": 69.2, "regularMarketOpen": 69.8, "regularMarketDayLow": 69.1, "regularMarketDayHigh": 70.5, "dividendRate": 9.13, "dividendYield": 0.1312, "exDividendDate": 1669939200, "payoutRatio": 1.5991, "beta": 0.188648, "trailingPE": 12.224169, "volume": 9036, "regularMarketVolume": 9036, "averageVolume": 12600, "averageVolume10days": 7501, "averageDailyVolume10Day": 7501, "bid": 69.3, "ask": 69.8, "bidSize": 0, "askSize": 0, "marketCap": 3548701952, "fiftyTwoWeekLow": 64.3, "fiftyTwoWeekHigh": 76.0, "priceToSalesTrailing12Months": 1.1651407, "fiftyDayAverage": 69.512, "twoHundredDayAverage": 67.949, "trailingAnnualDividendRate": 6.149, "trailingAnnualDividendYield": 0.08885839, "currency": "TWD", "enterpriseValue": 4036683264, "profitMargins": 0.09856, "sharesOutstanding": 50841000, "heldPercentInsiders": 0.8258, "heldPercentInstitutions": 0.00606, "impliedSharesOutstanding": 0, "bookValue": 23.764, "priceToBook": 2.937216, "lastFiscalYearEnd": 1672444800, "nextFiscalYearEnd": 1703980800, "mostRecentQuarter": 1672444800, "earningsQuarterlyGrowth": -0.052, "netIncomeToCommon": 300199008, "trailingEps": 5.71, "enterpriseToRevenue": 1.325, "enterpriseToEbitda": 8.998, "52WeekChange": -0.045517266, "SandP52WeekChange": 0.026524067, "lastDividendValue": 3.131017, "lastDividendDate": 1669939200, "exchange": "TAI", "quoteType": "EQUITY", "symbol": "1341.TW", "underlyingSymbol": "1341.TW", "shortName": "FULIN PLASTIC INDUSTRY(CAYMAN) ", "longName": "Fulin Plastic Industry (Cayman) Holding Co., Ltd.", "firstTradeDateEpochUtc": 1545613200, "timeZoneFullName": "Asia/Taipei", "timeZoneShortName": "CST", "uuid": "28309197-e3c4-3778-870e-b2047cce02ab", "messageBoardId": "finmb_572067046", "gmtOffSetMilliseconds": 28800000, "currentPrice": 69.8, "recommendationKey": "none", "totalCash": 361451008, "totalCashPerShare": 7.109, "ebitda": 448632992, "totalDebt": 874852992, "quickRatio": 0.785, "currentRatio": 1.429, "totalRevenue": 3045728000, "debtToEquity": 72.411, "revenuePerShare": 60.363, "returnOnAssets": 0.09243, "returnOnEquity": 0.24200001, "grossProfits": 603418000, "freeCashflow": 282616640, "operatingCashflow": 487224000, "earningsGrowth": 0.072, "revenueGrowth": -0.058, "grossMargins": 0.19812, "ebitdaMargins": 0.14729999, "operatingMargins": 0.11698, "financialCurrency": "TWD", "trailingPegRatio": null}