{"address1": "No. 19-9, San Chong Road", "address2": "5th Floor Nan-Kang", "city": "Taipei", "zip": "11501", "country": "Taiwan", "phone": "886 2 2655 3333", "fax": "886 2 2655 2212", "website": "https://www.teco.com.tw", "industry": "Specialty Industrial Machinery", "sector": "Industrials", "longBusinessSummary": "TECO Electric & Machinery Co., Ltd. engages in the manufacture, installation, wholesale, and retail of electronic equipment, telecommunication equipment, office equipment, and home appliances worldwide. It offers low, medium, and high voltage motors; system and automation products comprising AC servo driving systems, programmable logic controllers, human-machine interfaces, and robots; electromechanical engineering and power equipment; and household and air conditioning appliances. The company also develops wind turbines, electric cars, and PV power station products; and integrates Internet of Things. In addition, it manufactures and sells switches, busway and related components, touch-tone phone systems, billing boxes, generators, reducers, electric control products, and air conditioners mechanical equipment; invests, research, and develops software and hardware products related to fiber optic communications products; and constructs commercial buildings. Further, the company offers investment consultancy services for domestic and foreign industrial parks and lands; communication network information technology; science park development; develops and sells software; and provides storage and energy technical services. Additionally, it engages in the real estate business; international trading; production of data storage and processing equipment; other mail services; services related to information software, data processing, and electronic information supply; and import, sale, and lease of franking machines. The company was incorporated in 1956 and is headquartered in Taipei, Taiwan.", "companyOfficers": [{"maxAge": 1, "name": "Mr. Chao-Kai  Liu", "title": "MD & Director", "fiscalYear": 2014, "totalPay": 19240, "exercisedValue": 0, "unexercisedValue": 0}, {"maxAge": 1, "name": "Mr. Thomas  Fann", "age": 60, "title": "Pres & Chief Information Security Officer", "yearBorn": 1962, "exercisedValue": 0, "unexercisedValue": 0}, {"maxAge": 1, "name": "Mr. Tommy  Wu", "title": "Accounting Chief", "exercisedValue": 0, "unexercisedValue": 0}, {"maxAge": 1, "name": "Mr. Cheng-Tsung  Huang", "title": "MD & Director", "exercisedValue": 0, "unexercisedValue": 0}, {"maxAge": 1, "name": "Mr. Hong-Hsiang  Lin", "title": "Exec. Consultant", "exercisedValue": 0, "unexercisedValue": 0}, {"maxAge": 1, "name": "Mr. Yu-Ren  Huang", "title": "Managing Director", "exercisedValue": 0, "unexercisedValue": 0}, {"maxAge": 1, "name": "Mr. Shih-Hsiung  Chien", "title": "Head of Corp. Governance & Corp. Governance Officer", "exercisedValue": 0, "unexercisedValue": 0}, {"maxAge": 1, "name": "Mr. Sheng-Chyuan  Lin", "title": "Assistant VP & Exec. Officer", "exercisedValue": 0, "unexercisedValue": 0}, {"maxAge": 1, "name": "Mr. An-bing  Liu", "title": "Director of Financial Management Center", "exercisedValue": 0, "unexercisedValue": 0}, {"maxAge": 1, "name": "Sung-Pin  Chang", "title": "Assistant VP & Exec. Officer", "exercisedValue": 0, "unexercisedValue": 0}], "compensationAsOfEpochDate": 1419984000, "maxAge": 86400, "priceHint": 2, "previousClose": 44.0, "open": 44.0, "dayLow": 42.85, "dayHigh": 44.25, "regularMarketPreviousClose": 44.0, "regularMarketOpen": 44.0, "regularMarketDayLow": 42.85, "regularMarketDayHigh": 44.25, "dividendRate": 1.35, "dividendYield": 0.03, "exDividendDate": 1655251200, "payoutRatio": 0.8232, "fiveYearAvgDividendYield": 3.83, "beta": 0.367415, "trailingPE": 26.707317, "forwardPE": 15.103448, "volume": 22459815, "regularMarketVolume": 22459815, "averageVolume": 25783897, "averageVolume10days": 36842292, "averageDailyVolume10Day": 36842292, "bid": 43.75, "ask": 43.85, "bidSize": 0, "askSize": 0, "marketCap": 92386459648, "fiftyTwoWeekLow": 26.3, "fiftyTwoWeekHigh": 47.4, "priceToSalesTrailing12Months": 1.58426, "fiftyDayAverage": 35.881, "twoHundredDayAverage": 30.30825, "trailingAnnualDividendRate": 1.5, "trailingAnnualDividendYield": 0.03409091, "currency": "TWD", "enterpriseValue": 92631465984, "profitMargins": 0.05929, "floatShares": 1520519557, "sharesOutstanding": 2109280000, "heldPercentInsiders": 0.25203, "heldPercentInstitutions": 0.30388, "bookValue": 37.939, "priceToBook": 1.1544849, "lastFiscalYearEnd": 1672444800, "nextFiscalYearEnd": 1703980800, "mostRecentQuarter": 1672444800, "earningsQuarterlyGrowth": 0.122, "netIncomeToCommon": 3457667072, "trailingEps": 1.64, "forwardEps": 2.9, "pegRatio": 2.86, "lastSplitFactor": "102:100", "lastSplitDate": 1060041600, "enterpriseToRevenue": 1.588, "enterpriseToEbitda": 14.664, "exchange": "TAI", "quoteType": "EQUITY", "symbol": "1504.TW", "underlyingSymbol": "1504.TW", "shortName": "TECO ELECTRIC & MACHINERY CO", "longName": "TECO Electric & Machinery Co., Ltd.", "firstTradeDateEpochUtc": 946947600, "timeZoneFullName": "Asia/Taipei", "timeZoneShortName": "CST", "uuid": "7a90823a-308f-3a29-99fd-2de391f3350c", "gmtOffSetMilliseconds": 28800000, "currentPrice": 43.8, "targetHighPrice": 52.0, "targetLowPrice": 30.0, "targetMeanPrice": 37.67, "targetMedianPrice": 31.0, "recommendationMean": 2.0, "recommendationKey": "buy", "numberOfAnalystOpinions": 3, "totalCash": 21949857792, "totalCashPerShare": 10.406, "ebitda": 6316941824, "totalDebt": 15479265280, "quickRatio": 1.592, "currentRatio": 2.221, "totalRevenue": 58315214848, "debtToEquity": 17.933, "revenuePerShare": 27.647, "returnOnAssets": 0.02409, "returnOnEquity": 0.043870002, "grossProfits": 13185299000, "freeCashflow": 3262028800, "operatingCashflow": 6377629184, "earningsGrowth": 0.135, "revenueGrowth": 0.094, "grossMargins": 0.22610001, "ebitdaMargins": 0.10832, "operatingMargins": 0.087, "financialCurrency": "TWD", "trailingPegRatio": null}