{"address1": "No. 19, Innovation 1st Road", "address2": "Hsinchu Science Park", "city": "Hsinchu City", "zip": "30076", "country": "Taiwan", "phone": "886 3 578 6005", "fax": "886 3 578 6006", "website": "https://www.sunplus.com", "industry": "Semiconductors", "sector": "Technology", "longBusinessSummary": "Sunplus Technology Company Limited, together with its subsidiaries, provides consumer integrated circuits (ICs) for multimedia and automotive applications primarily in Taiwan, other Asian countries, and internationally. The company offers IC solutions for multimedia and automotive applications, such as DVD player, portable DVD player, home entertainment audio products, and car infotainment and advanced driving assistance systems; automotive ICs; intelligent acoustic solutions; system-in-package architecture; IP solutions; and media player ICs. Its products are used in consumer, portable, and connected device applications. Sunplus Technology Company Limited was incorporated in 1990 and is headquartered in Hsinchu City, Taiwan.", "companyOfficers": [{"maxAge": 1, "name": "Mr. Chou-Chye  Huang", "title": "CEO & Chairman", "fiscalYear": 2013, "totalPay": 10919484, "exercisedValue": 0, "unexercisedValue": 0}, {"maxAge": 1, "name": "Ms. Shu-Chen  Cheng", "title": "Director of Fin. & Accounting Division", "exercisedValue": 0, "unexercisedValue": 0}, {"maxAge": 1, "name": "Ji-An  Zhuang", "title": "Investor Relations Mang.", "exercisedValue": 0, "unexercisedValue": 0}, {"maxAge": 1, "name": "Ms. Phoebe  Chen", "title": "Head of Corp. Governance", "exercisedValue": 0, "unexercisedValue": 0}], "compensationAsOfEpochDate": 1388448000, "maxAge": 86400, "priceHint": 2, "previousClose": 23.1, "open": 23.0, "dayLow": 22.9, "dayHigh": 23.4, "regularMarketPreviousClose": 23.1, "regularMarketOpen": 23.0, "regularMarketDayLow": 22.9, "regularMarketDayHigh": 23.4, "dividendRate": 2.0, "dividendYield": 0.0853, "exDividendDate": 1657756800, "payoutRatio": 5.4054, "fiveYearAvgDividendYield": 3.71, "beta": 0.876021, "trailingPE": 63.24324, "forwardPE": 11.641791, "volume": 556151, "regularMarketVolume": 556151, "averageVolume": 1818377, "averageVolume10days": 805055, "averageDailyVolume10Day": 805055, "bid": 23.35, "ask": 23.4, "bidSize": 0, "askSize": 0, "marketCap": 13769378816, "fiftyTwoWeekLow": 20.25, "fiftyTwoWeekHigh": 37.25, "priceToSalesTrailing12Months": 2.0533817, "fiftyDayAverage": 24.826, "twoHundredDayAverage": 24.7835, "trailingAnnualDividendRate": 0.0, "trailingAnnualDividendYield": 0.0, "currency": "TWD", "enterpriseValue": 12414057472, "profitMargins": 0.0322, "floatShares": 459714844, "sharesOutstanding": 588435008, "heldPercentInsiders": 0.23459, "heldPercentInstitutions": 0.07113, "bookValue": 15.74, "priceToBook": 1.4866582, "lastFiscalYearEnd": 1672444800, "nextFiscalYearEnd": 1703980800, "mostRecentQuarter": 1672444800, "netIncomeToCommon": 215899008, "trailingEps": 0.37, "forwardEps": 2.01, "lastSplitFactor": "105:100", "lastSplitDate": 1220313600, "enterpriseToRevenue": 1.851, "enterpriseToEbitda": 17.1, "exchange": "TAI", "quoteType": "EQUITY", "symbol": "2401.TW", "underlyingSymbol": "2401.TW", "shortName": "SUNPLUS TECHNOLOGY", "longName": "Sunplus Technology Company Limited", "firstTradeDateEpochUtc": 946947600, "timeZoneFullName": "Asia/Taipei", "timeZoneShortName": "CST", "uuid": "31dd8065-ae34-3096-9ab0-b100ba34ac06", "gmtOffSetMilliseconds": 28800000, "currentPrice": 23.4, "recommendationMean": 3.0, "recommendationKey": "hold", "totalCash": 5110344192, "totalCashPerShare": 8.685, "ebitda": 725952000, "totalDebt": 1252760960, "quickRatio": 3.528, "currentRatio": 4.903, "totalRevenue": 6705708032, "debtToEquity": 10.675, "revenuePerShare": 11.396, "returnOnAssets": 0.011460001, "returnOnEquity": 0.05515, "grossProfits": 3300767000, "freeCashflow": -855260352, "operatingCashflow": -315729984, "revenueGrowth": -0.424, "grossMargins": 0.49223, "ebitdaMargins": 0.108260006, "operatingMargins": 0.042930003, "financialCurrency": "TWD", "trailingPegRatio": null}