{"address1": "No. 1, Dusing 1st Road", "address2": "Hsinchu Science Park", "city": "Hsinchu City", "zip": "30078", "country": "Taiwan", "phone": "886 3 5670 766", "fax": "886 3 5787 610", "website": "https://www.mediatek.com", "industry": "Semiconductors", "sector": "Technology", "longBusinessSummary": "MediaTek Inc. researches, develops, produces, and markets integrated circuits (ICs) in worldwide. It provides multimedia, computer peripherals oriented, consumer-oriented, and other application ICs. The company offers mobile communication, tablet, automotive chipsets; bluetooth, wireless LAN chips; artificial intelligence of things device SoCs; global positioning satellite chips; smart home connectivity chips; optical storage chipsets; bio-sensing analog front-end chips; DVD player SoCs; blu-ray DVD player chipsets; digital TV controller chips; power management and controller chips for various electronics; and USB PD type-c controller chips. It also provides wireless communication chipsets are mainly used in smartphones, tablets, chromebook, and feature phones; and NFC and wireless charging chips are mainly used in mobile phones, routers, TVs, set-up-boxes, smart wearables, smart home appliances, internet of things applications, game consoles, notebooks, and portable navigation devices. In addition, the company offers digital TV decoder and demodulator chips are used to receive and decode digital TV signals from either satellite, terrestrial or cable for video, as well as video on demand via ethernet and Wi-Fi; and ASIC chips are mainly used in consumer and enterprise electronics. Further, it provides xDSL chipsets are mainly used in DSL and fiber-optic modems, wired DSL router, and IAD gateway; and automotive SoC for eCockpit, telematics, and mmWave radar. Additionally, the company is involved in the provision of software and hardware design, development, test, maintenance and repair, and technological consultation services; import and export of its products; sale and delegation of patents and circuit layout rights for its products; and investment activities. It also provides research, marketing, and technology services; and intellectual property right management services. The company was incorporated in 1997 and is headquartered in Hsinchu, Taiwan.", "companyOfficers": [{"maxAge": 1, "name": "Dr. Lih Shyng  Tsai Ph.D.", "age": 71, "title": "Vice Chairman, CEO & Pres", "yearBorn": 1951, "fiscalYear": 2021, "totalPay": 18025000, "exercisedValue": 0, "unexercisedValue": 0}, {"maxAge": 1, "name": "Mr. David  Ku", "age": 52, "title": "Corp. Exec. VP, CFO & Spokesman", "yearBorn": 1970, "exercisedValue": 0, "unexercisedValue": 0}, {"maxAge": 1, "name": "Dr. Kevin  Jou", "title": "Corp. Exec. VP & CTO", "exercisedValue": 0, "unexercisedValue": 0}, {"maxAge": 1, "name": "Ms. Jessie  Wang", "title": "Deputy Director of Investor Relations & Analyst Relations Division", "exercisedValue": 0, "unexercisedValue": 0}, {"maxAge": 1, "name": "Mr. David  Su", "title": "Corp. Governance Officer, Corp. Sr. VP & Gen. Counsel", "exercisedValue": 0, "unexercisedValue": 0}, {"maxAge": 1, "name": "Ms. Sherry  Lin", "title": "Corp. Sr. VP & CHRO", "exercisedValue": 0, "unexercisedValue": 0}, {"maxAge": 1, "name": "Mr. Cheng-Te  Chuang", "title": "Corp. Exec. VP", "exercisedValue": 0, "unexercisedValue": 0}, {"maxAge": 1, "name": "Mr. Ji-Chang  Hsu", "title": "Corp. Sr. VP", "exercisedValue": 0, "unexercisedValue": 0}, {"maxAge": 1, "name": "Dr. Kou-Hung  Loh", "title": "Corp. Sr. VP", "exercisedValue": 0, "unexercisedValue": 0}, {"maxAge": 1, "name": "Mr. Jerry  Yu", "title": "Corp. Sr. VP", "exercisedValue": 0, "unexercisedValue": 0}], "compensationAsOfEpochDate": 1640908800, "maxAge": 86400, "priceHint": 2, "previousClose": 673.0, "open": 676.0, "dayLow": 665.0, "dayHigh": 679.0, "regularMarketPreviousClose": 673.0, "regularMarketOpen": 676.0, "regularMarketDayLow": 665.0, "regularMarketDayHigh": 679.0, "dividendRate": 73.0, "dividendYield": 0.108100004, "exDividendDate": 1655942400, "payoutRatio": 0.9834, "fiveYearAvgDividendYield": 4.15, "beta": 1.205497, "trailingPE": 8.956229, "forwardPE": 10.693038, "volume": 5449299, "regularMarketVolume": 5449299, "averageVolume": 6270796, "averageVolume10days": 7494092, "averageDailyVolume10Day": 7494092, "bid": 665.0, "ask": 666.0, "bidSize": 0, "askSize": 0, "marketCap": 1058560344064, "fiftyTwoWeekLow": 533.0, "fiftyTwoWeekHigh": 935.0, "priceToSalesTrailing12Months": 1.9288775, "fiftyDayAverage": 751.02, "twoHundredDayAverage": 677.33, "trailingAnnualDividendRate": 76.0, "trailingAnnualDividendYield": 0.11292719, "currency": "TWD", "enterpriseValue": 922117734400, "profitMargins": 0.21527, "floatShares": 1504053224, "sharesOutstanding": 1591820032, "heldPercentInsiders": 0.081709996, "heldPercentInstitutions": 0.478, "impliedSharesOutstanding": 0, "bookValue": 276.513, "priceToBook": 2.4049501, "lastFiscalYearEnd": 1672444800, "nextFiscalYearEnd": 1703980800, "mostRecentQuarter": 1672444800, "earningsQuarterlyGrowth": -0.385, "netIncomeToCommon": 118141108224, "trailingEps": 74.25, "forwardEps": 62.19, "pegRatio": 11.18, "lastSplitFactor": "102:100", "lastSplitDate": 1280275200, "enterpriseToRevenue": 1.68, "enterpriseToEbitda": 6.556, "52WeekChange": -0.20960188, "SandP52WeekChange": -0.033239067, "lastDividendValue": 73.00106, "lastDividendDate": 1655942400, "exchange": "TAI", "quoteType": "EQUITY", "symbol": "2454.TW", "underlyingSymbol": "2454.TW", "shortName": "MEDIATEK INC", "longName": "MediaTek Inc.", "firstTradeDateEpochUtc": 995850000, "timeZoneFullName": "Asia/Taipei", "timeZoneShortName": "CST", "uuid": "a3f15428-33e2-31a5-9952-086f78282e38", "messageBoardId": "finmb_6043453", "gmtOffSetMilliseconds": 28800000, "currentPrice": 665.0, "targetHighPrice": 950.0, "targetLowPrice": 467.0, "targetMeanPrice": 743.51, "targetMedianPrice": 784.5, "recommendationMean": 2.5, "recommendationKey": "buy", "numberOfAnalystOpinions": 20, "totalCash": 164809523200, "totalCashPerShare": 103.547, "ebitda": 140658589696, "totalDebt": 12803736576, "quickRatio": 1.565, "currentRatio": 2.103, "totalRevenue": 548796039168, "debtToEquity": 2.89, "revenuePerShare": 346.506, "returnOnAssets": 0.12486, "returnOnEquity": 0.27061, "grossProfits": 270904435000, "freeCashflow": 66245206016, "operatingCashflow": 144582803456, "earningsGrowth": -0.386, "revenueGrowth": -0.159, "grossMargins": 0.49363, "ebitdaMargins": 0.2563, "operatingMargins": 0.23103, "financialCurrency": "TWD", "trailingPegRatio": 1.686}