{"address1": "No. 99, Xing-fu Road", "address2": "Taoyuan District", "city": "Taoyuan City", "country": "Taiwan", "phone": "886 3 3261611", "fax": "886 3 3254241", "website": "https://www.meiloon.com.tw", "industry": "Consumer Electronics", "sector": "Technology", "longBusinessSummary": "Meiloon Industrial Co., Ltd. operates as an ODM/OEM manufacturer for audio systems and loudspeakers worldwide. It offers studio monitor, wireless and portable, in-wall/in-ceiling, professional audio, car, garden speakers, and other products, as well as home theater systems, such as sound bars. The company was founded in 1973 and is based in Taoyuan City, Taiwan.", "fullTimeEmployees": 1872, "companyOfficers": [{"maxAge": 1, "name": "W. J. Wu", "title": "Chairman and Chief Exec. Officer", "exercisedValue": 0, "unexercisedValue": 0}], "maxAge": 86400, "priceHint": 2, "previousClose": 20.55, "open": 20.25, "dayLow": 20.0, "dayHigh": 20.25, "regularMarketPreviousClose": 20.55, "regularMarketOpen": 20.25, "regularMarketDayLow": 20.0, "regularMarketDayHigh": 20.25, "dividendRate": 0.8, "dividendYield": 0.0388, "exDividendDate": 1682553600, "payoutRatio": 7.75, "beta": 0.34094, "trailingPE": 40.5, "volume": 67586, "regularMarketVolume": 67586, "averageVolume": 100480, "averageVolume10days": 24327, "averageDailyVolume10Day": 24327, "bid": 20.15, "ask": 20.2, "bidSize": 0, "askSize": 0, "marketCap": 3203307008, "fiftyTwoWeekLow": 19.4, "fiftyTwoWeekHigh": 32.125, "priceToSalesTrailing12Months": 0.91763294, "fiftyDayAverage": 21.058, "twoHundredDayAverage": 22.466688, "trailingAnnualDividendRate": 0.8, "trailingAnnualDividendYield": 0.038929444, "currency": "TWD", "enterpriseValue": 2570990848, "profitMargins": 0.026719999, "sharesOutstanding": 126858000, "heldPercentInsiders": 0.52112, "heldPercentInstitutions": 0.0063899998, "bookValue": 25.557, "priceToBook": 0.79234654, "lastFiscalYearEnd": 1672444800, "nextFiscalYearEnd": 1703980800, "mostRecentQuarter": 1672444800, "netIncomeToCommon": 93292000, "trailingEps": 0.5, "lastSplitFactor": "0:1", "lastSplitDate": 1353542400, "enterpriseToRevenue": 0.736, "enterpriseToEbitda": 24.137, "exchange": "TAI", "quoteType": "EQUITY", "symbol": "2477.TW", "underlyingSymbol": "2477.TW", "shortName": "MEILOON INDUSTRIAL CO", "longName": "Meiloon Industrial Co., Ltd.", "firstTradeDateEpochUtc": 951354000, "timeZoneFullName": "Asia/Taipei", "timeZoneShortName": "CST", "uuid": "a1ea0afa-9350-31f1-91a2-f860b5b2faac", "gmtOffSetMilliseconds": 28800000, "currentPrice": 20.25, "recommendationKey": "none", "totalCash": 2944753920, "totalCashPerShare": 18.57, "ebitda": 106515000, "totalDebt": 1918349952, "quickRatio": 1.823, "currentRatio": 2.864, "totalRevenue": 3490836992, "debtToEquity": 43.764, "revenuePerShare": 22.014, "returnOnAssets": -0.00091, "returnOnEquity": 0.01863, "freeCashflow": 52943624, "operatingCashflow": 341164992, "revenueGrowth": -0.397, "grossMargins": 0.13786, "ebitdaMargins": 0.03051, "operatingMargins": -0.00356, "financialCurrency": "TWD", "trailingPegRatio": null}