{"address1": "No. 1, Songzhi Rd.", "address2": "24F., Xinyi Dist.", "city": "Taipei", "zip": "110", "country": "Taiwan", "phone": "886 2 2723 0887", "fax": "886 2 2723 1979", "website": "https://www.passivecomponent.com", "industry": "Electronic Components", "sector": "Technology", "longBusinessSummary": "Walsin Technology Corporation engages in the development, manufacture, and sale of passive electronic components in Taiwan and internationally. It provides capacitors, resistors, thin film products, inductors, safety components, RF filters, antennas, and modules. The company's products are used in mobile communication, networking, automotive, industrial, power supply, IoT, green energy, PC and peripheral, and lighting applications. Walsin Technology Corporation was founded in 1970 and is headquartered in Taipei, Taiwan.", "companyOfficers": [{"maxAge": 1, "name": "Mr. Lee-Chin  Ku", "title": "Pres", "exercisedValue": 0, "unexercisedValue": 0}, {"maxAge": 1, "name": "Mr. Tse-Kuang  Yeh", "title": "Head of Financial & Accounting and Assistant VP", "exercisedValue": 0, "unexercisedValue": 0}, {"maxAge": 1, "name": "Ms. Yeh-Jeng  Chen", "title": "Assistant VP, Legal Counsel, Chief Legal Officer & Head of Corp. Governance", "exercisedValue": 0, "unexercisedValue": 0}, {"maxAge": 1, "name": "Mingcan  Zeng", "title": "Gen. Mang.", "exercisedValue": 0, "unexercisedValue": 0}, {"maxAge": 1, "name": "Mr. Jui-Tsung  Chang", "title": "Exec. VP and R&D Officer", "exercisedValue": 0, "unexercisedValue": 0}, {"maxAge": 1, "name": "Jui Chang  Huang", "title": "Chief Internal Auditor", "exercisedValue": 0, "unexercisedValue": 0}], "maxAge": 86400, "priceHint": 2, "previousClose": 102.0, "open": 102.5, "dayLow": 97.0, "dayHigh": 103.5, "regularMarketPreviousClose": 102.0, "regularMarketOpen": 102.5, "regularMarketDayLow": 97.0, "regularMarketDayHigh": 103.5, "dividendRate": 4.51, "dividendYield": 0.0438, "exDividendDate": 1660089600, "payoutRatio": 1.3461, "fiveYearAvgDividendYield": 4.36, "beta": 1.383841, "trailingPE": 28.985075, "forwardPE": 5.5868816, "volume": 5727510, "regularMarketVolume": 5727510, "averageVolume": 4209945, "averageVolume10days": 7058035, "averageDailyVolume10Day": 7058035, "bid": 97.1, "ask": 97.2, "bidSize": 0, "askSize": 0, "marketCap": 47074467840, "fiftyTwoWeekLow": 71.6, "fiftyTwoWeekHigh": 131.0, "priceToSalesTrailing12Months": 1.3336616, "fiftyDayAverage": 98.44, "twoHundredDayAverage": 89.474, "trailingAnnualDividendRate": 0.0, "trailingAnnualDividendYield": 0.0, "currency": "TWD", "enterpriseValue": 61733945344, "profitMargins": 0.04676, "floatShares": 300336078, "sharesOutstanding": 484804000, "heldPercentInsiders": 0.39113998, "heldPercentInstitutions": 0.08565, "impliedSharesOutstanding": 0, "bookValue": 91.338, "priceToBook": 1.0630844, "lastFiscalYearEnd": 1672444800, "nextFiscalYearEnd": 1703980800, "mostRecentQuarter": 1672444800, "netIncomeToCommon": 1650587008, "trailingEps": 3.35, "forwardEps": 17.38, "lastSplitFactor": "0:1", "lastSplitDate": 1504742400, "enterpriseToRevenue": 1.749, "enterpriseToEbitda": 8.315, "52WeekChange": -0.20155036, "SandP52WeekChange": -0.033239067, "lastDividendValue": 4.509282, "lastDividendDate": 1660089600, "exchange": "TAI", "quoteType": "EQUITY", "symbol": "2492.TW", "underlyingSymbol": "2492.TW", "shortName": "WALSIN TECHNOLOGY CORP", "longName": "Walsin Technology Corporation", "firstTradeDateEpochUtc": 946947600, "timeZoneFullName": "Asia/Taipei", "timeZoneShortName": "CST", "uuid": "07db1ce7-89a3-3d69-b161-ce28d61a5027", "messageBoardId": "finmb_9649231", "gmtOffSetMilliseconds": 28800000, "currentPrice": 97.1, "recommendationMean": 3.0, "recommendationKey": "hold", "totalCash": 23650504704, "totalCashPerShare": 48.784, "ebitda": 7424662016, "totalDebt": 26631331840, "quickRatio": 1.749, "currentRatio": 2.188, "totalRevenue": 35297161216, "debtToEquity": 49.7, "revenuePerShare": 72.807, "returnOnAssets": 0.01386, "returnOnEquity": 0.042859998, "grossProfits": 6299748000, "freeCashflow": 70855624, "operatingCashflow": 8932537344, "revenueGrowth": -0.167, "grossMargins": 0.17848, "ebitdaMargins": 0.21034999, "operatingMargins": 0.058390003, "financialCurrency": "TWD", "trailingPegRatio": null}