{"address1": "No.92, Dunhua South Road", "address2": "9th Floor Section 2 Da\u2019an District", "city": "Taipei", "zip": "106", "country": "Taiwan", "phone": "886 2 2706 2929", "fax": "886 2 2708 1317", "website": "https://www.dacin.com.tw", "industry": "Engineering & Construction", "sector": "Industrials", "longBusinessSummary": "Da-Cin Construction Co.,Ltd. engages in the civil engineering and building construction in Taiwan, Singapore, Malaysia, and Vietnam. It operates through Engineering Department and Construction Department segments. The company offers engineering, procurement, and construction services for roads, bridges, tunnels, and hillside development; and housing complexes, commercial office buildings, schools, hotels, hospitals, supermarkets, department stores, shopping centers, deep-excavation and high rises, and other construction works. It also provides engineering, procurement, and construction services for wafer factories, LCD panel factories, glass substrate and passive component factories, IC packaging factories, and other high-tech compounds; and MRT, underground railways, and other transportation construction. In addition, the company offers land cooperation, real estate sales, and new home after sales services. Further, it engages in construction information and technology; construction management-related business; real estate construction and infrastructure related business; constructs, leases, and sells buildings; and manages investments in manufacturing and other industries. The company was incorporated in 1967 and is based in Taipei, Taiwan.", "companyOfficers": [{"maxAge": 1, "name": "Mr. Liao  Chao-Bang", "title": "CEO & Director", "exercisedValue": 0, "unexercisedValue": 0}, {"maxAge": 1, "name": "Mr. Jen-Tai  Wang", "title": "Founder", "exercisedValue": 0, "unexercisedValue": 0}, {"maxAge": 1, "name": "Linda  Chen", "title": "Assistant VP of Fin. Division", "exercisedValue": 0, "unexercisedValue": 0}, {"maxAge": 1, "name": "Mr. Mark  Pan", "title": "Sr. VP & Chief Engineer Office", "exercisedValue": 0, "unexercisedValue": 0}, {"maxAge": 1, "name": "Mr. Joseph  Lee", "title": "Chief Engineer", "exercisedValue": 0, "unexercisedValue": 0}, {"maxAge": 1, "name": "Mr. Kwok-Ho  Tam", "title": "Deputy Chief Engineer of Technical Division", "exercisedValue": 0, "unexercisedValue": 0}], "maxAge": 86400, "priceHint": 2, "previousClose": 32.05, "open": 32.0, "dayLow": 31.95, "dayHigh": 32.3, "regularMarketPreviousClose": 32.05, "regularMarketOpen": 32.0, "regularMarketDayLow": 31.95, "regularMarketDayHigh": 32.3, "dividendRate": 2.5, "dividendYield": 0.0774, "exDividendDate": 1681948800, "payoutRatio": 0.6964, "fiveYearAvgDividendYield": 7.26, "trailingPE": 9.044944, "volume": 575283, "regularMarketVolume": 575283, "averageVolume": 1007372, "averageVolume10days": 819205, "averageDailyVolume10Day": 819205, "bid": 32.2, "ask": 32.25, "bidSize": 0, "askSize": 0, "marketCap": 10542216192, "fiftyTwoWeekLow": 28.2, "fiftyTwoWeekHigh": 34.25, "fiftyDayAverage": 32.652, "twoHundredDayAverage": 30.894, "trailingAnnualDividendRate": 0.0, "trailingAnnualDividendYield": 0.0, "currency": "TWD", "profitMargins": 0.0, "sharesOutstanding": 324864000, "heldPercentInsiders": 0.25455, "heldPercentInstitutions": 0.03525, "bookValue": 28.469, "priceToBook": 1.1310549, "trailingEps": 3.56, "lastSplitFactor": "105:100", "lastSplitDate": 1158796800, "exchange": "TAI", "quoteType": "EQUITY", "symbol": "2535.TW", "underlyingSymbol": "2535.TW", "shortName": "DA-CIN CONSTRUCTION CO", "longName": "Da-Cin Construction Co.,Ltd.", "firstTradeDateEpochUtc": 946947600, "timeZoneFullName": "Asia/Taipei", "timeZoneShortName": "CST", "uuid": "b2ff5f9e-4f49-3a95-96a4-2d55b8253614", "gmtOffSetMilliseconds": 28800000, "currentPrice": 32.2, "recommendationKey": "none", "grossProfits": 2054882000, "grossMargins": 0.0, "ebitdaMargins": 0.0, "operatingMargins": 0.0, "financialCurrency": "TWD", "trailingPegRatio": null}