{"address1": "Taiwan Avenue", "address2": "4th Floor No. 239, Section 2 West District", "city": "Taichung", "zip": "403", "country": "Taiwan", "phone": "886 4 3600 5800", "fax": "886 4 3600 5799", "website": "https://www.sakurad.com.tw", "industry": "Real Estate\u2014Development", "sector": "Real Estate", "longBusinessSummary": "Sakura Development Co.,Ltd engages in the sale and lease of residential properties with focus on the Zhongzhangtou area in Taiwan. The company was founded in 1976 and is based in Taichung, Taiwan.", "fullTimeEmployees": 74, "companyOfficers": [{"maxAge": 1, "name": "Mr. Shih-Ying  Chen", "title": "GM, Pres & Director", "fiscalYear": 2021, "totalPay": 8068000, "exercisedValue": 0, "unexercisedValue": 0}, {"maxAge": 1, "name": "Ms. Shu-Chen  Shen", "title": "Mang. of Fin. Department, Accounting Supervisor, Financial Accounting Mang. & Director", "fiscalYear": 2021, "totalPay": 1721000, "exercisedValue": 0, "unexercisedValue": 0}, {"maxAge": 1, "name": "Mr. Yao-Chun  Chiang", "title": "Mang. of Admin. Department", "exercisedValue": 0, "unexercisedValue": 0}], "compensationAsOfEpochDate": 1640908800, "maxAge": 86400, "priceHint": 2, "previousClose": 37.15, "open": 37.2, "dayLow": 37.05, "dayHigh": 37.5, "regularMarketPreviousClose": 37.15, "regularMarketOpen": 37.2, "regularMarketDayLow": 37.05, "regularMarketDayHigh": 37.5, "dividendRate": 0.2, "dividendYield": 0.0053, "exDividendDate": 1661904000, "payoutRatio": 0.097399995, "fiveYearAvgDividendYield": 2.28, "beta": 0.043915, "trailingPE": 18.210785, "volume": 328182, "regularMarketVolume": 328182, "averageVolume": 355896, "averageVolume10days": 393036, "averageDailyVolume10Day": 393036, "bid": 37.15, "ask": 37.35, "bidSize": 0, "askSize": 0, "marketCap": 31664654336, "fiftyTwoWeekLow": 27.179792, "fiftyTwoWeekHigh": 38.2, "priceToSalesTrailing12Months": 5.0550613, "fiftyDayAverage": 35.667, "twoHundredDayAverage": 32.37346, "trailingAnnualDividendRate": 0.2, "trailingAnnualDividendYield": 0.00538358, "currency": "TWD", "enterpriseValue": 35737350144, "profitMargins": 0.24033001, "floatShares": 213183651, "sharesOutstanding": 852345984, "heldPercentInsiders": 0.75389, "heldPercentInstitutions": 0.00387, "impliedSharesOutstanding": 0, "bookValue": 13.551, "priceToBook": 2.7414954, "lastFiscalYearEnd": 1672444800, "nextFiscalYearEnd": 1703980800, "mostRecentQuarter": 1672444800, "netIncomeToCommon": 1505410048, "trailingEps": 2.04, "lastSplitFactor": "1142392:1000000", "lastSplitDate": 1661904000, "enterpriseToRevenue": 5.705, "enterpriseToEbitda": 18.501, "52WeekChange": 0.3146305, "SandP52WeekChange": -0.033239067, "lastDividendValue": 0.198762, "lastDividendDate": 1661904000, "exchange": "TAI", "quoteType": "EQUITY", "symbol": "2539.TW", "underlyingSymbol": "2539.TW", "shortName": "SAKURA DEVELOPMENT CO", "longName": "Sakura Development Co.,Ltd", "firstTradeDateEpochUtc": 946947600, "timeZoneFullName": "Asia/Taipei", "timeZoneShortName": "CST", "uuid": "aba45803-64d8-3395-8ec1-457ff7942c75", "messageBoardId": "finmb_9794106", "gmtOffSetMilliseconds": 28800000, "currentPrice": 37.15, "recommendationKey": "none", "totalCash": 102824000, "totalCashPerShare": 0.14, "ebitda": 1931608064, "totalDebt": 8533436928, "quickRatio": 0.022, "currentRatio": 2.629, "totalRevenue": 6263950848, "debtToEquity": 85.67, "revenuePerShare": 8.532, "returnOnAssets": 0.057389997, "returnOnEquity": 0.16319, "grossProfits": 2256763000, "freeCashflow": 822748608, "operatingCashflow": 1134756992, "revenueGrowth": -1.0, "grossMargins": 0.36028, "ebitdaMargins": 0.30837, "operatingMargins": 0.30762, "financialCurrency": "TWD", "trailingPegRatio": null}