{"address1": "No. 209, Civic Boulevard", "address2": "14th Floor Section 1 Datong District", "city": "Taipei City", "zip": "103", "country": "Taiwan", "phone": "886 2 7733 8888", "fax": "886 2 2555 3900", "website": "https://www.radium.com.tw", "industry": "Real Estate\u2014Diversified", "sector": "Real Estate", "longBusinessSummary": "Radium Life Tech Co., Ltd. develops, sells, manages, and leases public housing, commercial building, and industrial zone projects in Taiwan. It operates through Construction, Leasing, Shopping Mall Business, Sewage Treatment, and Others segments. The company also engages in the operation of transit stations, hotels, and shopping malls; civil construction and investment business; manufacture of biotechnology and cosmetic products; and provision of energy technical, and business and corporate management consulting services. In addition, it is involved in the elder care, property management, and resource cycle businesses. Radium Life Tech Co., Ltd. was founded in 1980 and is based in Taipei City, Taiwan.", "companyOfficers": [{"maxAge": 1, "name": "Mr. Rong Shian  Lin", "title": "CEO & Chairman", "exercisedValue": 0, "unexercisedValue": 0}, {"maxAge": 1, "name": "Mr. Hua Chun  Lin", "title": "Vice Chairman, Vice CEO, Group Pres & Unified Procurement Center Pres", "exercisedValue": 0, "unexercisedValue": 0}, {"maxAge": 1, "name": "Mr. Yao Kai  Liu", "title": "Pres & Director", "exercisedValue": 0, "unexercisedValue": 0}, {"maxAge": 1, "name": "Ms. Tina  Chen", "title": "VP of Fin. Division & Corp. Governance Officer and Fin. Officer", "exercisedValue": 0, "unexercisedValue": 0}, {"maxAge": 1, "name": "Mr. Kerwin  Go", "title": "Group Pres, Operation & Management Center Pres and Representative Director", "exercisedValue": 0, "unexercisedValue": 0}, {"maxAge": 1, "name": "Ms. Rita  Liu", "title": "Associate VP of Accounting Division", "exercisedValue": 0, "unexercisedValue": 0}, {"maxAge": 1, "name": "Mr. Henry  Tsao", "title": "VP of Admin. & Management Center", "exercisedValue": 0, "unexercisedValue": 0}, {"maxAge": 1, "name": "Ms. Christine  Chen", "title": "Associate VP of Investor & PR Office", "exercisedValue": 0, "unexercisedValue": 0}, {"maxAge": 1, "name": "Ms. Chia Hui  Lee", "title": "Associate VP of Legal Division", "exercisedValue": 0, "unexercisedValue": 0}, {"maxAge": 1, "name": "Mr. Chug Chun  Liu", "title": "Head of Environmental Engineering Division", "exercisedValue": 0, "unexercisedValue": 0}], "maxAge": 86400, "priceHint": 2, "previousClose": 9.16, "open": 9.2, "dayLow": 9.1, "dayHigh": 9.2, "regularMarketPreviousClose": 9.16, "regularMarketOpen": 9.2, "regularMarketDayLow": 9.1, "regularMarketDayHigh": 9.2, "dividendRate": 0.2, "dividendYield": 0.0217, "exDividendDate": 1660003200, "payoutRatio": 2.5, "beta": 0.455246, "trailingPE": 114.12501, "volume": 633405, "regularMarketVolume": 633405, "averageVolume": 1004681, "averageVolume10days": 1813040, "averageDailyVolume10Day": 1813040, "bid": 9.13, "ask": 9.14, "bidSize": 0, "askSize": 0, "marketCap": 8035267072, "fiftyTwoWeekLow": 8.81, "fiftyTwoWeekHigh": 10.4, "priceToSalesTrailing12Months": 1.3706486, "fiftyDayAverage": 9.2258, "twoHundredDayAverage": 9.3034, "trailingAnnualDividendRate": 0.0, "trailingAnnualDividendYield": 0.0, "currency": "TWD", "enterpriseValue": 44482248704, "profitMargins": 0.01268, "floatShares": 476245617, "sharesOutstanding": 880094976, "heldPercentInsiders": 0.43330002, "heldPercentInstitutions": 0.0643, "impliedSharesOutstanding": 0, "bookValue": 12.369, "priceToBook": 0.73813564, "lastFiscalYearEnd": 1672444800, "nextFiscalYearEnd": 1703980800, "mostRecentQuarter": 1672444800, "earningsQuarterlyGrowth": -0.829, "netIncomeToCommon": 74309000, "trailingEps": 0.08, "lastSplitFactor": "1020:1000", "lastSplitDate": 1565222400, "enterpriseToRevenue": 7.588, "enterpriseToEbitda": 23.4, "52WeekChange": -0.10146344, "SandP52WeekChange": -0.033239067, "lastDividendValue": 0.2, "lastDividendDate": 1660003200, "exchange": "TAI", "quoteType": "EQUITY", "symbol": "2547.TW", "underlyingSymbol": "2547.TW", "shortName": "RADIUM LIFE TECH CO", "longName": "Radium Life Tech. Co., Ltd.", "firstTradeDateEpochUtc": 977878800, "timeZoneFullName": "Asia/Taipei", "timeZoneShortName": "CST", "uuid": "9ef54fea-e33a-3967-a22f-004f24e674fd", "messageBoardId": "finmb_9858033", "gmtOffSetMilliseconds": 28800000, "currentPrice": 9.13, "recommendationKey": "none", "totalCash": 3247932928, "totalCashPerShare": 3.69, "ebitda": 1900912000, "totalDebt": 38846193664, "quickRatio": 0.241, "currentRatio": 0.79, "totalRevenue": 5862383104, "debtToEquity": 331.776, "revenuePerShare": 6.655, "returnOnAssets": 0.01119, "returnOnEquity": 0.0087, "grossProfits": 2909790000, "freeCashflow": 1729017344, "operatingCashflow": 440724992, "earningsGrowth": -0.843, "revenueGrowth": -0.425, "grossMargins": 0.49635, "ebitdaMargins": 0.32424998, "operatingMargins": 0.17304, "financialCurrency": "TWD", "trailingPegRatio": null}