{"address1": "No 23. Li-Hsin Road", "address2": "Hsinchu Science Park", "city": "Hsinchu City", "zip": "300", "country": "Taiwan", "phone": "886 3 666 1818", "fax": "886 3 666 1919", "website": "https://www.rad-ic.com", "industry": "Semiconductors", "industryDisp": "Semiconductors", "sector": "Technology", "longBusinessSummary": "Raydium Semiconductor Corporation provides integrated circuit (IC) solutions in Taiwan and internationally. It offers driver IC, power IC, touch control IC, and power management and timing controller IC solutions for artificial intelligence, Internet of Things, smart TVs, professional gaming, computer information, automotive, and industrial control products, as well as mobile and wearable devices. The company was founded in 2003 and is headquartered in Hsinchu City, Taiwan.", "companyOfficers": [{"maxAge": 1, "name": "Ying-Lie  Chen", "title": "VP", "exercisedValue": 0, "unexercisedValue": 0}, {"maxAge": 1, "name": "Shang-Ping  Tang", "title": "VP", "exercisedValue": 0, "unexercisedValue": 0}, {"maxAge": 1, "name": "Yao-Yu  Huang", "title": "VP", "exercisedValue": 0, "unexercisedValue": 0}, {"maxAge": 1, "name": "Wen-Cong  Lin", "title": "VP", "exercisedValue": 0, "unexercisedValue": 0}], "maxAge": 86400, "priceHint": 2, "previousClose": 355.5, "open": 350.5, "dayLow": 334.0, "dayHigh": 350.5, "regularMarketPreviousClose": 355.5, "regularMarketOpen": 350.5, "regularMarketDayLow": 334.0, "regularMarketDayHigh": 350.5, "dividendRate": 45.0, "dividendYield": 0.120799996, "exDividendDate": 1656892800, "payoutRatio": 0.91129994, "beta": 1.166893, "trailingPE": 6.8131204, "forwardPE": 11.123967, "volume": 2493035, "regularMarketVolume": 2493035, "averageVolume": 1200668, "averageVolume10days": 742322, "averageDailyVolume10Day": 742322, "bid": 336.5, "ask": 337.0, "marketCap": 25525274624, "fiftyTwoWeekLow": 197.0, "fiftyTwoWeekHigh": 522.0, "priceToSalesTrailing12Months": 1.1184423, "fiftyDayAverage": 404.71, "twoHundredDayAverage": 316.505, "trailingAnnualDividendRate": 41.0, "trailingAnnualDividendYield": 0.11533052, "currency": "TWD", "enterpriseValue": 17430521856, "profitMargins": 0.16924, "floatShares": 61403105, "sharesOutstanding": 75855200, "heldPercentInsiders": 0.24211, "heldPercentInstitutions": 0.15822, "impliedSharesOutstanding": 0, "bookValue": 170.555, "priceToBook": 1.9729707, "lastFiscalYearEnd": 1672444800, "nextFiscalYearEnd": 1703980800, "mostRecentQuarter": 1672444800, "earningsQuarterlyGrowth": -0.672, "netIncomeToCommon": 3862336000, "trailingEps": 49.39, "forwardEps": 30.25, "enterpriseToRevenue": 0.764, "enterpriseToEbitda": 4.517, "52WeekChange": -0.2974308, "SandP52WeekChange": 0.026524067, "lastDividendValue": 45.0, "lastDividendDate": 1656892800, "exchange": "TAI", "quoteType": "EQUITY", "symbol": "3592.TW", "underlyingSymbol": "3592.TW", "shortName": "RAYDIUM SEMI-CONDUCTOR CORPORAT", "longName": "Raydium Semiconductor Corporation", "firstTradeDateEpochUtc": 1641776400, "timeZoneFullName": "Asia/Taipei", "timeZoneShortName": "CST", "uuid": "2be35fa3-2840-35c0-9f1c-09e79a54f4bb", "messageBoardId": "finmb_35245578", "gmtOffSetMilliseconds": 28800000, "currentPrice": 336.5, "targetHighPrice": 750.0, "targetLowPrice": 360.0, "targetMeanPrice": 468.75, "targetMedianPrice": 382.5, "recommendationMean": 3.0, "recommendationKey": "hold", "numberOfAnalystOpinions": 4, "totalCash": 10879066112, "totalCashPerShare": 143.419, "ebitda": 3859097088, "totalDebt": 53601000, "quickRatio": 2.071, "currentRatio": 2.642, "totalRevenue": 22822164480, "debtToEquity": 0.414, "revenuePerShare": 302.729, "returnOnAssets": 0.111499995, "returnOnEquity": 0.35159, "grossProfits": 9236681000, "freeCashflow": 2281287168, "operatingCashflow": 3963365120, "earningsGrowth": -0.708, "revenueGrowth": -0.37, "grossMargins": 0.40472, "ebitdaMargins": 0.16909, "operatingMargins": 0.15937, "financialCurrency": "TWD", "trailingPegRatio": null}