{"address1": "No. 15, Caigong 1st Road", "address2": "Lane 62 Zuoying District", "city": "Kaohsiung", "country": "Taiwan", "phone": "886 7 343 3776", "fax": "886 7 343 3639", "website": "https://www.logah.com", "industry": "Electronic Components", "sector": "Technology", "longBusinessSummary": "Logah Technology Corp. engages in the manufacture of automatic pinning, molding, cold, hot gloss, plating and assembly products. It provides plastic body parts of conference display, 3C products, displays, mobile phone, and household products; curved displays; headphone, charger, power bank, and electroacoustic plastic shell products; two-material injection molding, smart speakers, tablets, and vacuum cleaner products; and automotive interior, energy, and outdoor products. Logah Technology Corp. was founded in 2003 and is headquartered in Kaohsiung, Taiwan.", "companyOfficers": [{"maxAge": 1, "name": "Mr. Hui Fa  Yu", "title": "Chairman & GM", "exercisedValue": 0, "unexercisedValue": 0}, {"maxAge": 1, "name": "Liang  Xinjin", "title": "Sr. Mang. of Accounting & Admin. Office", "exercisedValue": 0, "unexercisedValue": 0}], "maxAge": 86400, "priceHint": 2, "previousClose": 12.55, "open": 12.5, "dayLow": 12.45, "dayHigh": 12.5, "regularMarketPreviousClose": 12.55, "regularMarketOpen": 12.5, "regularMarketDayLow": 12.45, "regularMarketDayHigh": 12.5, "exDividendDate": 1315526400, "payoutRatio": 0.0, "beta": 0.419376, "volume": 46197, "regularMarketVolume": 46197, "averageVolume": 55528, "averageVolume10days": 25465, "averageDailyVolume10Day": 25465, "bid": 12.45, "ask": 12.5, "bidSize": 0, "askSize": 0, "marketCap": 1163025024, "fiftyTwoWeekLow": 11.9, "fiftyTwoWeekHigh": 17.3, "priceToSalesTrailing12Months": 1.2588282, "fiftyDayAverage": 12.579, "twoHundredDayAverage": 13.53225, "trailingAnnualDividendRate": 0.0, "trailingAnnualDividendYield": 0.0, "currency": "TWD", "enterpriseValue": 1532781312, "profitMargins": -0.10034, "sharesOutstanding": 93042000, "heldPercentInsiders": 0.60912, "heldPercentInstitutions": 0.0, "impliedSharesOutstanding": 0, "bookValue": 5.748, "priceToBook": 2.1746695, "lastFiscalYearEnd": 1672444800, "nextFiscalYearEnd": 1703980800, "mostRecentQuarter": 1672444800, "netIncomeToCommon": -92703000, "trailingEps": -1.0, "lastSplitFactor": "559:1000", "lastSplitDate": 1539820800, "enterpriseToRevenue": 1.659, "enterpriseToEbitda": 287.145, "52WeekChange": -0.09642857, "SandP52WeekChange": -0.033239067, "lastDividendValue": 1.788368, "lastDividendDate": 1315526400, "exchange": "TAI", "quoteType": "EQUITY", "symbol": "3593.TW", "underlyingSymbol": "3593.TW", "shortName": "LOGAH TECHNOLOGY CORP.", "longName": "Logah Technology Corp.", "firstTradeDateEpochUtc": 1199062800, "timeZoneFullName": "Asia/Taipei", "timeZoneShortName": "CST", "uuid": "99a35d10-0cf2-3561-9876-54b97252cd6f", "messageBoardId": "finmb_33597792", "gmtOffSetMilliseconds": 28800000, "currentPrice": 12.5, "recommendationKey": "none", "totalCash": 126708000, "totalCashPerShare": 1.362, "ebitda": 5338000, "totalDebt": 491807008, "quickRatio": 0.555, "currentRatio": 0.701, "totalRevenue": 923894976, "debtToEquity": 91.961, "revenuePerShare": 9.93, "returnOnAssets": -0.03018, "returnOnEquity": -0.16128999, "grossProfits": 44943000, "freeCashflow": -66418752, "operatingCashflow": -119865000, "revenueGrowth": -0.219, "grossMargins": 0.048639998, "ebitdaMargins": 0.0057800002, "operatingMargins": -0.07534, "financialCurrency": "TWD", "trailingPegRatio": null}