{"address1": "Ugland House", "address2": "PO Box 309", "city": "Grand Cayman", "zip": "KY1-1104", "country": "Cayman Islands", "website": "https://www.bonnyworldwide.com", "industry": "Leisure", "industryDisp": "Leisure", "sector": "Consumer Cyclical", "longBusinessSummary": "Bonny Worldwide Limited, together with its subsidiaries, engages in the manufacture and sale of OEM and ODM carbon fiber rackets and related sporting goods. The company offers hockey sticks, tennis and badminton rackets, and carbon fiber rims. It also provides helmets for the goalkeepers, carbon fiber car wheels, squash rackets, etc.; and accessories, such as shuttlecocks, tennis balls, athletic shoes, sportswear, travel bags, etc. The company offers its products under the BONNY brand name. In addition, it operates and manages a sports center. The company has operations in North America, Mainland China, Taiwan, and internationally. Bonny Worldwide Limited was founded in 1982 and is headquartered in Grand Cayman, the Cayman Islands.", "fullTimeEmployees": 1037, "companyOfficers": [{"maxAge": 1, "name": "Mr. Jin-San  Hong", "title": "GM & Director", "exercisedValue": 0, "unexercisedValue": 0}, {"maxAge": 1, "name": "Ms. Pei-Chun  Tai", "title": "Fin. & Accounting Division Director", "exercisedValue": 0, "unexercisedValue": 0}, {"maxAge": 1, "name": "Fang-Ming  Lo", "title": "Chief Information Security Officer", "exercisedValue": 0, "unexercisedValue": 0}, {"maxAge": 1, "name": "Mr. Wen-Dan  Hong", "title": "Deputy GM & Brand Sales Division Director and Director", "exercisedValue": 0, "unexercisedValue": 0}], "maxAge": 86400, "priceHint": 2, "previousClose": 55.9, "open": 54.9, "dayLow": 54.8, "dayHigh": 56.0, "regularMarketPreviousClose": 55.9, "regularMarketOpen": 54.9, "regularMarketDayLow": 54.8, "regularMarketDayHigh": 56.0, "dividendRate": 12.0, "dividendYield": 0.2024, "exDividendDate": 1671667200, "payoutRatio": 0.6631, "fiveYearAvgDividendYield": 4.12, "beta": 0.279632, "trailingPE": 7.4797845, "volume": 14000, "regularMarketVolume": 14000, "averageVolume": 52570, "averageVolume10days": 40300, "averageDailyVolume10Day": 40300, "bid": 55.5, "ask": 55.8, "bidSize": 0, "askSize": 0, "marketCap": 2749136896, "fiftyTwoWeekLow": 38.95, "fiftyTwoWeekHigh": 79.8, "priceToSalesTrailing12Months": 1.4057925, "fiftyDayAverage": 59.226, "twoHundredDayAverage": 59.12825, "trailingAnnualDividendRate": 5.0, "trailingAnnualDividendYield": 0.089445435, "currency": "TWD", "enterpriseValue": 3431326208, "profitMargins": 0.20801, "sharesOutstanding": 49534000, "heldPercentInsiders": 0.59674, "heldPercentInstitutions": 0.0, "impliedSharesOutstanding": 0, "bookValue": 32.523, "priceToBook": 1.7064847, "lastFiscalYearEnd": 1672444800, "nextFiscalYearEnd": 1703980800, "mostRecentQuarter": 1672444800, "netIncomeToCommon": 406777984, "trailingEps": 7.42, "enterpriseToRevenue": 1.755, "enterpriseToEbitda": 6.735, "52WeekChange": 0.4223919, "SandP52WeekChange": 0.026524067, "lastDividendValue": 3.0, "lastDividendDate": 1671667200, "exchange": "TAI", "quoteType": "EQUITY", "symbol": "8467.TW", "underlyingSymbol": "8467.TW", "shortName": "BONNY WORLDWIDE LTD", "longName": "Bonny Worldwide Limited", "firstTradeDateEpochUtc": 1450141200, "timeZoneFullName": "Asia/Taipei", "timeZoneShortName": "CST", "uuid": "eb9f417c-a879-3dd0-b041-bfd8d14bb517", "messageBoardId": "finmb_265833840", "gmtOffSetMilliseconds": 28800000, "currentPrice": 55.5, "recommendationKey": "none", "totalCash": 688603008, "totalCashPerShare": 13.902, "ebitda": 509481984, "totalDebt": 1182822016, "quickRatio": 0.687, "currentRatio": 1.345, "totalRevenue": 1955577984, "debtToEquity": 73.433, "revenuePerShare": 39.48, "returnOnAssets": 0.081709996, "returnOnEquity": 0.26543, "freeCashflow": -3254875, "operatingCashflow": 169942000, "revenueGrowth": 0.171, "grossMargins": 0.37674, "ebitdaMargins": 0.26053, "operatingMargins": 0.20104, "financialCurrency": "TWD", "trailingPegRatio": null}